LICENSE
MANIFEST.in
README.md
package.json
setup.py
dash_devextreme/Accordion.py
dash_devextreme/Bullet.py
dash_devextreme/Button.py
dash_devextreme/Chart.py
dash_devextreme/CheckBox.py
dash_devextreme/CircularGauge.py
dash_devextreme/DDDataGrid.py
dash_devextreme/DataGrid.py
dash_devextreme/DateBox.py
dash_devextreme/Drawer.py
dash_devextreme/DropDownButton.py
dash_devextreme/FileUploader.py
dash_devextreme/Form.py
dash_devextreme/FormButtonItem.py
dash_devextreme/FormEmptyItem.py
dash_devextreme/FormGroupItem.py
dash_devextreme/FormSimpleItem.py
dash_devextreme/FormTab.py
dash_devextreme/FormTabbedItem.py
dash_devextreme/Gallery.py
dash_devextreme/LinearGauge.py
dash_devextreme/List.py
dash_devextreme/LoadPanel.py
dash_devextreme/Loading.py
dash_devextreme/Loading2.py
dash_devextreme/LoadingPanel.py
dash_devextreme/Lookup.py
dash_devextreme/NumberBox.py
dash_devextreme/PieChart.py
dash_devextreme/PivotGrid.py
dash_devextreme/Popover.py
dash_devextreme/Popup.py
dash_devextreme/RadioInput.py
dash_devextreme/ScrollView.py
dash_devextreme/SelectBox.py
dash_devextreme/SimpleBoxView.py
dash_devextreme/SimpleRadioInput.py
dash_devextreme/Switch.py
dash_devextreme/TabPanel.py
dash_devextreme/Tabs.py
dash_devextreme/TextArea.py
dash_devextreme/TextBox.py
dash_devextreme/Toolbar.py
dash_devextreme/ToolbarItem.py
dash_devextreme/Tooltip.py
dash_devextreme/TreeList.py
dash_devextreme/Validator.py
dash_devextreme/ValidatorStringLengthRule.py
dash_devextreme/__init__.py
dash_devextreme/_imports_.py
dash_devextreme/dash_devextreme.dev.js
dash_devextreme/dash_devextreme.dev.js.map
dash_devextreme/dash_devextreme.min.js
dash_devextreme/dash_devextreme.min.js.map
dash_devextreme/metadata.json
dash_devextreme/package.json
dash_devextreme/version.py
dash_devextreme.egg-info/PKG-INFO
dash_devextreme.egg-info/SOURCES.txt
dash_devextreme.egg-info/dependency_links.txt
dash_devextreme.egg-info/top_level.txt