Metadata-Version: 2.1
Name: dash-devextreme
Version: 0.16.5
Summary: Wrapper of DevExtreme components for Plotly Dash
Home-page: UNKNOWN
Author: Sergei Pikhovkin <s@pikhovkin.ru>
License: MIT
Platform: UNKNOWN
Classifier: Environment :: Web Environment
Classifier: License :: OSI Approved :: MIT License
Classifier: Programming Language :: Python :: 2.7
Classifier: Programming Language :: Python :: 3
Classifier: Framework :: Dash
